pubarchiver/__init__.py
pubarchiver/__main__.py
pubarchiver/article.py
pubarchiver/exceptions.py
pubarchiver/data/JATS-Archiving-1-2-MathML3-DTD/BITS-embedded-index2.ent
pubarchiver/data/JATS-Archiving-1-2-MathML3-DTD/JATS-XHTMLtablesetup1.ent
pubarchiver/data/JATS-Archiving-1-2-MathML3-DTD/JATS-ali-namespace1.ent
pubarchiver/data/JATS-Archiving-1-2-MathML3-DTD/JATS-archivearticle1-mathml3.dtd
pubarchiver/data/JATS-Archiving-1-2-MathML3-DTD/JATS-archivecustom-classes1.ent
pubarchiver/data/JATS-Archiving-1-2-MathML3-DTD/JATS-archivecustom-mixes1.ent
pubarchiver/data/JATS-Archiving-1-2-MathML3-DTD/JATS-archivecustom-models1.ent
pubarchiver/data/JATS-Archiving-1-2-MathML3-DTD/JATS-archivecustom-modules1.ent
pubarchiver/data/JATS-Archiving-1-2-MathML3-DTD/JATS-articlemeta1.ent
pubarchiver/data/JATS-Archiving-1-2-MathML3-DTD/JATS-backmatter1.ent
pubarchiver/data/JATS-Archiving-1-2-MathML3-DTD/JATS-chars1.ent
pubarchiver/data/JATS-Archiving-1-2-MathML3-DTD/JATS-common-atts1.ent
pubarchiver/data/JATS-Archiving-1-2-MathML3-DTD/JATS-common1.ent
pubarchiver/data/JATS-Archiving-1-2-MathML3-DTD/JATS-default-classes1.ent
pubarchiver/data/JATS-Archiving-1-2-MathML3-DTD/JATS-default-mixes1.ent
pubarchiver/data/JATS-Archiving-1-2-MathML3-DTD/JATS-display1.ent
pubarchiver/data/JATS-Archiving-1-2-MathML3-DTD/JATS-format1.ent
pubarchiver/data/JATS-Archiving-1-2-MathML3-DTD/JATS-funding1.ent
pubarchiver/data/JATS-Archiving-1-2-MathML3-DTD/JATS-journalmeta1.ent
pubarchiver/data/JATS-Archiving-1-2-MathML3-DTD/JATS-link1.ent
pubarchiver/data/JATS-Archiving-1-2-MathML3-DTD/JATS-list1.ent
pubarchiver/data/JATS-Archiving-1-2-MathML3-DTD/JATS-math1.ent
pubarchiver/data/JATS-Archiving-1-2-MathML3-DTD/JATS-mathml3-mathmlsetup1.ent
pubarchiver/data/JATS-Archiving-1-2-MathML3-DTD/JATS-mathml3-modules1.ent
pubarchiver/data/JATS-Archiving-1-2-MathML3-DTD/JATS-modules1.ent
pubarchiver/data/JATS-Archiving-1-2-MathML3-DTD/JATS-nlmcitation1.ent
pubarchiver-2.1.2.dist-info/LICENSE
pubarchiver-2.1.2.dist-info/METADATA
pubarchiver-2.1.2.dist-info/WHEEL
pubarchiver-2.1.2.dist-info/entry_points.txt
pubarchiver-2.1.2.dist-info/top_level.txt
pubarchiver-2.1.2.dist-info/RECORD
