Metadata-Version: 2.1
Name: pubarchiver
Version: 2.1.2
Summary: Archive journal articles into Portico and PMC
Home-page: https://github.com/caltechlibrary/pubarchiver
Author: Michael Hucka, Tom Morrell
Author-email: mhucka@caltech.edu, tmorrell@library.caltech.edu
License: BSD 3-clause
Project-URL: Source Code, https://github.com/caltechlibrary/pubarchiver
Project-URL: Bug Tracker, https://github.com/caltechlibrary/pubarchiver/issues
Keywords: journal publishing,archiving
Platform: UNKNOWN
Classifier: Development Status :: 5 - Production/Stable
Classifier: Environment :: Console
Classifier: Intended Audience :: Science/Research
Classifier: License :: OSI Approved :: BSD License
Classifier: Operating System :: MacOS :: MacOS X
Classifier: Operating System :: Microsoft :: Windows
Classifier: Operating System :: POSIX
Classifier: Operating System :: POSIX :: Linux
Classifier: Operating System :: Unix
Classifier: Programming Language :: Python
Classifier: Programming Language :: Python :: 3.5
Classifier: Topic :: System :: Archiving
Classifier: Topic :: System :: Archiving :: Packaging
Classifier: Topic :: Utilities
Requires-Python: >=3.5
License-File: LICENSE
Requires-Dist: beautifulsoup4 (>=4.9.3)
Requires-Dist: bun (>=0.0.8)
Requires-Dist: commonpy (>=1.8.2)
Requires-Dist: crossrefapi (>=1.5.0)
Requires-Dist: dateparser (>=1.0.0)
Requires-Dist: humanize (>=3.9.0)
Requires-Dist: lxml (>=4.6.3)
Requires-Dist: Pillow (>=8.3.2)
Requires-Dist: plac (>=1.3.3)
Requires-Dist: pypubsub (>=4.0.3)
Requires-Dist: recordclass (>=0.14.3)
Requires-Dist: setuptools (>=58.3.0)
Requires-Dist: sidetrack (>=2.0.0)
Requires-Dist: urllib3 (>=1.26.5)
Requires-Dist: xmltodict (>=0.12.0)
